aioquery/__init__.py
aioquery/data_operations.py
aioquery/decorators.py
aioquery/exceptions.py
aioquery/models.py
aioquery/tests/test_server.py
aioquery-1.1.6.dist-info/LICENSE
aioquery-1.1.6.dist-info/METADATA
aioquery-1.1.6.dist-info/WHEEL
aioquery-1.1.6.dist-info/top_level.txt
aioquery-1.1.6.dist-info/RECORD
