Metadata-Version: 2.1
Name: aioquery
Version: 1.1.6
Summary: Asynchronous source A2S.
Home-page: https://aioquery.readthedocs.io/en/latest/
Author: WardPearce
Author-email: wardpearce@protonmail.com
License: Apache-2.0 License
Platform: UNKNOWN
Requires-Python: >=3.6
License-File: LICENSE
Requires-Dist: asyncio-dgram (>=1.0.1)
Requires-Dist: asynctest (>=0.13.)
Requires-Dist: sphinxcontrib-trio
Requires-Dist: sphinx-material
